nanollama.py
nanollama-0.0.6.dist-info/LICENSE
nanollama-0.0.6.dist-info/METADATA
nanollama-0.0.6.dist-info/WHEEL
nanollama-0.0.6.dist-info/entry_points.txt
nanollama-0.0.6.dist-info/top_level.txt
nanollama-0.0.6.dist-info/RECORD
