Metadata-Version: 2.2
Name: nanollama
Version: 0.0.6
Summary: Nano Llama
Home-page: https://github.com/JosefAlbers/nanollama32
Author: Josef Albers
Author-email: albersj66@gmail.com
License: MIT
Requires-Python: >=3.12.8
License-File: LICENSE
Requires-Dist: mlx==0.22.0
Requires-Dist: numpy==2.2.2
Requires-Dist: huggingface-hub==0.28.1
Requires-Dist: tiktoken==0.8.0
Dynamic: author
Dynamic: author-email
Dynamic: description
Dynamic: description-content-type
Dynamic: home-page
Dynamic: license
Dynamic: requires-dist
Dynamic: requires-python
Dynamic: summary
